{
        "ir_report_custom": {
                "migrate": false, 
                "on": "source", 
                "depends": false, 
                "transformation": null
        }, 
        "ir_act_report_custom": {
                "migrate": false, 
                "on": "source", 
                "depends": false, 
                "transformation": null
        }, 
        "res_request": {
                "migrate": false, 
                "on": "both", 
                "depends": false, 
                "transformation": null
        }, 
        "maintenance_contract_module": {
                "migrate": false, 
                "on": "source", 
                "depends": false, 
                "transformation": null
        }, 
        "res_config_users": {
                "migrate": false, 
                "on": "target", 
                "depends": false, 
                "transformation": null
        }, 
        "publisher_warranty_contract": {
                "migrate": false, 
                "on": "target", 
                "depends": false, 
                "transformation": null
        }, 
        "ir_report_custom_fields": {
                "migrate": false, 
                "on": "source", 
                "depends": false, 
                "transformation": null
        }, 
        "ir_act_report_xml": {
                "on": "both", 
                "target": [
                        "report_file", 
                        "report_type"
                ], 
                "migrate": false, 
                "source": [
                        "report_type"
                ], 
                "depends": false, 
                "transformation": null, 
                "delete": false
        }, 
        "res_payterm": {
                "migrate": false, 
                "on": "both", 
                "depends": false, 
                "transformation": null
        }, 
        "res_company": {
                "on": "both", 
                "target": [
                        "rml_header3", 
                        "account_no"
                ], 
                "migrate": false, 
                "source": [], 
                "depends": false, 
                "transformation": null, 
                "delete": false
        }, 
        "wkf_instance": {
                "on": "both", 
                "target": [], 
                "migrate": false, 
                "source": [
                        "uid"
                ], 
                "depends": false, 
                "transformation": null, 
                "delete": false
        }, 
        "ir_actions": {
                "migrate": false, 
                "on": "both", 
                "depends": false, 
                "transformation": null
        }, 
        "res_request_history": {
                "migrate": false, 
                "on": "both", 
                "depends": false, 
                "transformation": null
        }, 
        "res_widget": {
                "migrate": false, 
                "on": "target", 
                "depends": false, 
                "transformation": null
        }, 
        "res_partner_canal": {
                "migrate": false, 
                "on": "both", 
                "depends": false, 
                "transformation": null
        }, 
        "ir_attachment": {
                "on": "both", 
                "target": [
                        "type", 
                        "company_id", 
                        "name", 
                        "res_name", 
                        "datas_fname", 
                        "url"
                ], 
                "migrate": false, 
                "source": [
                        "datas_fname", 
                        "name", 
                        "link"
                ], 
                "depends": false, 
                "transformation": null, 
                "delete": false
        }, 
        "ir_model_access": {
                "migrate": false, 
                "on": "both", 
                "depends": false, 
                "transformation": null
        }, 
        "res_partner": {
                "on": "both", 
                "target": [
                        "company_id", 
                        "employee", 
                        "title"
                ], 
                "migrate": true, 
                "source": [
                        "title"
                ], 
                "depends": ["res_partner_title"], 
                "transformation": [
                        "model-ktr/base/res_partner.ktr"
                ], 
                "delete": false
        }, 
        "res_request_link": {
                "migrate": false, 
                "on": "both", 
                "depends": false, 
                "transformation": null
        }, 
        "ir_actions_todo": {
                "on": "both", 
                "target": [
                        "restart"
                ], 
                "migrate": false, 
                "source": [
                        "end_date", 
                        "active", 
                        "start_date", 
                        "type", 
                        "start_on"
                ], 
                "depends": false, 
                "transformation": null, 
                "delete": false
        }, 
        "ir_property": {
                "on": "both", 
                "target": [
                        "value_reference", 
                        "type", 
                        "value_binary", 
                        "value_integer", 
                        "value_text", 
                        "value_datetime", 
                        "value_float"
                ], 
                "migrate": false, 
                "source": [
                        "value"
                ], 
                "depends": false, 
                "transformation": [
                        "model-ktr/base/ir_property.ktr"
                ], 
                "delete": false
        }, 
        "ir_rule_group": {
                "migrate": false, 
                "on": "source", 
                "depends": false, 
                "transformation": null
        }, 
        "res_country_state": {
                "migrate": false, 
                "on": "both", 
                "depends": false, 
                "transformation": null
        }, 
        "res_partner_title": {
                "migrate": true, 
                "on": "both", 
                "depends": false,
                "execute": [
                        "model-ktr/base/res_partner_title.ktr"
                ],
                "transformation": []
        }, 
        "ir_sequence_type": {
                "migrate": false, 
                "on": "both", 
                "depends": false, 
                "transformation": null
        }, 
        "ir_module_repository": {
                "migrate": false, 
                "on": "source", 
                "depends": false, 
                "transformation": null
        }, 
        "res_partner_bank": {
                "migrate": false, 
                "on": "both", 
                "depends": false, 
                "transformation": null
        }, 
        "res_currency": {
                "on": "both", 
                "target": [
                        "rounding", 
                        "date", 
                        "symbol", 
                        "base", 
                        "company_id"
                ], 
                "migrate": false, 
                "source": [
                        "code", 
                        "rounding"
                ], 
                "depends": false, 
                "transformation": null, 
                "delete": false
        }, 
        "wkf_workitem": {
                "migrate": false, 
                "on": "both", 
                "depends": false, 
                "transformation": null
        }, 
        "ir_ui_view_custom": {
                "migrate": false, 
                "on": "both", 
                "depends": false, 
                "transformation": null
        }, 
        "ir_act_wizard": {
                "migrate": false, 
                "on": "both", 
                "depends": false, 
                "transformation": null
        }, 
        "ir_model_config": {
                "migrate": false, 
                "on": "source", 
                "depends": false, 
                "transformation": null
        }, 
        "ir_values": {
                "migrate": false, 
                "on": "both", 
                "depends": false, 
                "transformation": null
        }, 
        "res_lang": {
                "on": "both", 
                "target": [
                        "iso_code", 
                        "code"
                ], 
                "migrate": false, 
                "source": [
                        "code"
                ], 
                "depends": false, 
                "transformation": null, 
                "delete": false
        }, 
        "res_country": {
                "migrate": false, 
                "on": "both", 
                "depends": false, 
                "transformation": null
        }, 
        "res_groups": {
                "migrate": false, 
                "on": "both", 
                "depends": false, 
                "transformation": null
        }, 
        "res_partner_address": {
                "on": "both", 
                "target": [
                        "company_id", 
                        "function", 
                        "title"
                ], 
                "migrate": false, 
                "source": [
                        "function", 
                        "title"
                ], 
                "depends": false, 
                "transformation": [
                        "model-ktr/base/res_partner_address.ktr"
                ], 
                "delete": false
        }, 
        "wkf_activity": {
                "migrate": false, 
                "on": "both", 
                "depends": false, 
                "transformation": null
        }, 
        "ir_ui_view_sc": {
                "migrate": false, 
                "on": "both", 
                "depends": false, 
                "transformation": null
        }, 
        "ir_act_url": {
                "migrate": false, 
                "on": "both", 
                "depends": false, 
                "transformation": null
        }, 
        "ir_exports_line": {
                "migrate": false, 
                "on": "both", 
                "depends": false, 
                "transformation": null
        }, 
        "ir_filters": {
                "migrate": false, 
                "on": "target", 
                "depends": false, 
                "transformation": null
        }, 
        "ir_module_category": {
                "migrate": false, 
                "on": "both", 
                "depends": false, 
                "transformation": null
        }, 
        "wkf": {
                "migrate": false, 
                "on": "both", 
                "depends": false, 
                "transformation": null
        }, 
        "res_partner_event": {
                "on": "both", 
                "target": [], 
                "migrate": false, 
                "source": [
                        "event_ical_id", 
                        "type", 
                        "document", 
                        "som", 
                        "partner_type", 
                        "planned_revenue", 
                        "canal_id", 
                        "probability", 
                        "planned_cost"
                ], 
                "depends": false, 
                "transformation": null, 
                "delete": false
        }, 
        "res_currency_rate": {
                "on": "both", 
                "target": [
                        "rate"
                ], 
                "migrate": false, 
                "source": [
                        "rate"
                ], 
                "depends": false, 
                "transformation": null, 
                "delete": false
        }, 
        "ir_server_object_lines": {
                "migrate": false, 
                "on": "both", 
                "depends": false, 
                "transformation": null
        }, 
        "wkf_triggers": {
                "migrate": false, 
                "on": "both", 
                "depends": false, 
                "transformation": null
        }, 
        "res_partner_bank_type": {
                "migrate": false, 
                "on": "both", 
                "depends": false, 
                "transformation": null
        }, 
        "maintenance_contract": {
                "migrate": false, 
                "on": "source", 
                "depends": false, 
                "transformation": null
        }, 
        "res_roles": {
                "migrate": false, 
                "on": "source", 
                "depends": false, 
                "transformation": null
        }, 
        "ir_cron": {
                "migrate": false, 
                "on": "both", 
                "depends": false, 
                "transformation": null
        }, 
        "ir_rule": {
                "on": "both", 
                "target": [
                        "perm_unlink", 
                        "perm_write", 
                        "domain_force", 
                        "model_id", 
                        "perm_read", 
                        "name", 
                        "perm_create", 
                        "global"
                ], 
                "migrate": false, 
                "source": [
                        "field_id", 
                        "operator", 
                        "rule_group", 
                        "domain_force", 
                        "operand"
                ], 
                "depends": false, 
                "transformation": null, 
                "delete": false
        }, 
        "res_partner_bank_type_field": {
                "migrate": false, 
                "on": "both", 
                "depends": false, 
                "transformation": null
        }, 
        "ir_default": {
                "migrate": false, 
                "on": "both", 
                "depends": false, 
                "transformation": null
        }, 
        "multi_company_default": {
                "migrate": false, 
                "on": "target", 
                "depends": false, 
                "transformation": null
        }, 
        "res_bank": {
                "migrate": false, 
                "on": "both", 
                "depends": false, 
                "transformation": null
        }, 
        "res_users": {
                "on": "both", 
                "target": [
                        "menu_tips", 
                        "email", 
                        "date"
                ], 
                "migrate": false, 
                "source": [], 
                "depends": false, 
                "transformation": null, 
                "delete": false
        }, 
        "ir_ui_menu": {
                "on": "both", 
                "target": [
                        "web_icon_data", 
                        "web_icon_hover_data", 
                        "web_icon", 
                        "web_icon_hover"
                ], 
                "migrate": false, 
                "source": [], 
                "depends": false, 
                "transformation": null, 
                "delete": false
        }, 
        "ir_ui_view": {
                "migrate": false, 
                "on": "both", 
                "depends": false, 
                "transformation": null
        }, 
        "ir_model": {
                "migrate": false, 
                "on": "both", 
                "depends": false, 
                "transformation": null
        }, 
        "res_partner_category": {
                "on": "both", 
                "target": [
                        "parent_left", 
                        "parent_right"
                ], 
                "migrate": false, 
                "source": [], 
                "depends": false, 
                "transformation": null, 
                "delete": false
        }, 
        "res_partner_som": {
                "migrate": false, 
                "on": "source", 
                "depends": false, 
                "transformation": null
        }, 
        "ir_model_fields": {
                "on": "both", 
                "target": [
                        "selectable"
                ], 
                "migrate": false, 
                "source": [], 
                "depends": false, 
                "transformation": null, 
                "delete": false
        }, 
        "ir_model_data": {
                "migrate": false, 
                "on": "both", 
                "depends": false, 
                "transformation": null
        }, 
        "wkf_transition": {
                "on": "both", 
                "target": [
                        "group_id"
                ], 
                "migrate": false, 
                "source": [
                        "role_id"
                ], 
                "depends": false, 
                "transformation": null, 
                "delete": false
        }, 
        "ir_act_window_view": {
                "migrate": false, 
                "on": "both", 
                "depends": false, 
                "transformation": null
        }, 
        "res_partner_event_type": {
                "migrate": false, 
                "on": "source", 
                "depends": false, 
                "transformation": null
        }, 
        "ir_act_window": {
                "on": "both", 
                "target": [
                        "help", 
                        "multi", 
                        "auto_search", 
                        "search_view_id", 
                        "filter", 
                        "menus"
                ], 
                "migrate": false, 
                "source": [], 
                "depends": false, 
                "transformation": null, 
                "delete": false
        }, 
        "ir_module_module": {
                "on": "both", 
                "target": [
                        "maintainer", 
                        "contributors", 
                        "web", 
                        "license"
                ], 
                "migrate": false, 
                "source": [
                        "license"
                ], 
                "depends": false, 
                "transformation": null, 
                "delete": false
        }, 
        "ir_module_module_dependency": {
                "migrate": false, 
                "on": "both", 
                "depends": false, 
                "transformation": null
        }, 
        "ir_sequence": {
                "on": "both", 
                "target": [
                        "company_id"
                ], 
                "migrate": false, 
                "source": [], 
                "depends": false, 
                "transformation": null, 
                "delete": false
        }, 
        "res_widget_user": {
                "migrate": false, 
                "on": "target", 
                "depends": false, 
                "transformation": null
        }, 
        "res_log": {
                "migrate": false, 
                "on": "target", 
                "depends": false, 
                "transformation": null
        }, 
        "res_partner_function": {
                "migrate": false, 
                "on": "source", 
                "depends": false, 
                "transformation": null
        }, 
        "ir_config_parameter": {
                "migrate": false, 
                "on": "target", 
                "depends": false, 
                "transformation": null
        }, 
        "ir_translation": {
                "on": "both", 
                "target": [
                        "lang", 
                        "module", 
                        "xml_id"
                ], 
                "migrate": false, 
                "source": [
                        "lang"
                ], 
                "depends": false, 
                "transformation": null, 
                "delete": false
        }, 
        "ir_exports": {
                "migrate": false, 
                "on": "both", 
                "depends": false, 
                "transformation": null
        }, 
        "ir_act_server": {
                "on": "both", 
                "target": [
                        "copy_object"
                ], 
                "migrate": false, 
                "source": [], 
                "depends": false, 
                "transformation": null, 
                "delete": false
        }
}
